ViStreamASR/__init__.py
ViStreamASR/cli.py
ViStreamASR/core.py
ViStreamASR/streaming.py
vistreamasr-0.1.3.dist-info/METADATA
vistreamasr-0.1.3.dist-info/WHEEL
vistreamasr-0.1.3.dist-info/entry_points.txt
vistreamasr-0.1.3.dist-info/top_level.txt
vistreamasr-0.1.3.dist-info/RECORD
