Metadata-Version: 2.4
Name: ViStreamASR
Version: 0.1.3
Summary: Vietnamese Streaming Automatic Speech Recognition Library
Home-page: https://github.com/nguyenvulebinh/ViStreamASR
Author: ViStreamASR Team
Author-email: nguyenvulebinh@gmail.com
Project-URL: Bug Reports, https://github.com/nguyenvulebinh/ViStreamASR/issues
Project-URL: Source, https://github.com/nguyenvulebinh/ViStreamASR
Project-URL: Documentation, https://github.com/nguyenvulebinh/ViStreamASR/blob/main/README.md
Keywords: speech recognition,asr,vietnamese,streaming,real-time,audio processing,machine learning,deep learning
Classifier: Development Status :: 4 - Beta
Classifier: Intended Audience :: Developers
Classifier: Intended Audience :: Science/Research
Classifier: License :: OSI Approved :: MIT License
Classifier: Operating System :: OS Independent
Classifier: Programming Language :: Python :: 3
Classifier: Programming Language :: Python :: 3.9
Classifier: Programming Language :: Python :: 3.10
Classifier: Programming Language :: Python :: 3.11
Classifier: Programming Language :: Python :: 3.12
Classifier: Topic :: Scientific/Engineering :: Artificial Intelligence
Classifier: Topic :: Multimedia :: Sound/Audio :: Speech
Requires-Python: >=3.9
Requires-Dist: torch>=2.5.0
Requires-Dist: torchaudio>=2.5.0
Requires-Dist: numpy>=1.19.0
Requires-Dist: requests>=2.25.0
Requires-Dist: flashlight-text
Requires-Dist: librosa
Provides-Extra: dev
Requires-Dist: pytest>=6.0; extra == "dev"
Requires-Dist: pytest-cov>=2.10; extra == "dev"
Requires-Dist: black>=21.0; extra == "dev"
Requires-Dist: flake8>=3.8; extra == "dev"
Requires-Dist: mypy>=0.800; extra == "dev"
Dynamic: author
Dynamic: author-email
Dynamic: classifier
Dynamic: description
Dynamic: description-content-type
Dynamic: home-page
Dynamic: keywords
Dynamic: project-url
Dynamic: provides-extra
Dynamic: requires-dist
Dynamic: requires-python
Dynamic: summary
